{
  "generated_at": "2026-07-20T16:01:35.637127+00:00",
  "total": 6,
  "online": 5,
  "offline": 1,
  "online_rate": 0.8333,
  "average_score": 81.65,
  "artifacts": {
    "tvbox": "output/tvbox.json",
    "warehouse": "output/warehouse.json",
    "adult_warehouse": "output/adult-warehouse.json",
    "all_lines": "output/all-lines.json",
    "m3u": "output/live.m3u",
    "adult_m3u": "output/adult-live.m3u",
    "summary": "output/summary.json",
    "selected": "5",
    "adult_selected": "0"
  }
}